{
    "collapse_output_transforms": true,
    "convergence_threshold": [ 1e-07, 1e-08 ],
    "convergence_window_size": [ 5, 3 ],
    "dimension": 3,
    "initial_moving_transform_com": 2,
    "interpolation": "LanczosWindowedSinc",
    "metric": [ "Mattes", "Mattes" ],
    "metric_weight": [ 1.0, 1.0 ],
    "number_of_iterations": [ [ 50 ], [ 20 ] ],
    "radius_or_number_of_bins": [ 32, 32 ],
    "sampling_percentage": [ 0.25, 0.5 ],
    "sampling_strategy": [ "Random", "Random" ],
    "shrink_factors": [ [ 2 ], [ 1 ] ],
    "sigma_units": [ "mm", "mm" ],
    "smoothing_sigmas": [ [ 8.0 ], [ 2.0 ] ],
    "transform_parameters": [ [ 0.1 ], [ 0.1 ] ],
    "transforms": [ "Rigid", "Rigid" ],
    "use_estimate_learning_rate_once": [ true, false ],
    "use_histogram_matching": [ true, true ],
    "winsorize_lower_quantile": 0.001,
    "winsorize_upper_quantile": 0.999
}